nerimity/__init__.py
nerimity/_enums.py
nerimity/attachment.py
nerimity/button.py
nerimity/buttoninteraction.py
nerimity/channel.py
nerimity/client.py
nerimity/context.py
nerimity/invite.py
nerimity/member.py
nerimity/message.py
nerimity/post.py
nerimity/roles.py
nerimity/server.py
nerimity/slashcommand.py
nerimity/status.py
nerimity-1.4.1.dist-info/licenses/LICENSE.TXT
nerimity-1.4.1.dist-info/METADATA
nerimity-1.4.1.dist-info/WHEEL
nerimity-1.4.1.dist-info/top_level.txt
nerimity-1.4.1.dist-info/RECORD
