Metadata-Version: 2.4
Name: nerimity
Version: 1.4.1
License-File: LICENSE.TXT
Requires-Dist: aiohttp>=3.11.13
Requires-Dist: websockets>=15.0.1
Requires-Dist: requests>=2.32.3
Dynamic: description
Dynamic: description-content-type
Dynamic: license-file
Dynamic: requires-dist
